zdsync/__init__.py
zdsync/cli.py
zdsync/client.py
zdsync/printer.py
zdsync/synchronizer.py
zdsync-0.0.3.dist-info/LICENSE.txt
zdsync-0.0.3.dist-info/METADATA
zdsync-0.0.3.dist-info/WHEEL
zdsync-0.0.3.dist-info/entry_points.txt
zdsync-0.0.3.dist-info/top_level.txt
zdsync-0.0.3.dist-info/RECORD
